art_engine/__init__.py
art_engine/appconfig.py
art_engine/cli.py
art_engine/complex_engine.py
art_engine/dna_generator.py
art_engine/engine.py
art_engine/engine_factory.py
art_engine/simple_engine.py
art_engine/commands/__init__.py
art_engine/commands/cmd_bake.py
art_engine/commands/cmd_dna.py
art_engine/commands/cmd_info.py
art_engine/commands/cmd_init.py
art_engine/commands/cmd_rarity.py
art_engine/commands/cmd_run.py
art_engine/commands/cmd_update-metadata.py
art_engine/commands/cmd_version.py
art_engine/config_files/complex_instance_config.py
art_engine/config_files/simple_instance_config.py
agentfud_art_engine-0.3.4.dist-info/LICENSE
agentfud_art_engine-0.3.4.dist-info/METADATA
agentfud_art_engine-0.3.4.dist-info/WHEEL
agentfud_art_engine-0.3.4.dist-info/entry_points.txt
agentfud_art_engine-0.3.4.dist-info/top_level.txt
agentfud_art_engine-0.3.4.dist-info/RECORD
