Metadata-Version: 2.1
Name: agentfud-art-engine
Version: 0.3.4
Summary: AgentFUD Art Engine
Home-page: https://github.com/AgentFUD/agentfud-art-engine
Author: AgentFUD
Author-email: agentfud@gmail.com
License: UNKNOWN
Keywords: python,python3,Art Engine,NFT Generator,NFT,Image generator
Platform: UNKNOWN
Classifier: Programming Language :: Python :: 3
Classifier: License :: OSI Approved :: MIT License
Classifier: Operating System :: OS Independent
Requires-Python: >=3.6
Requires-Dist: Pillow (==8.4.0)
Requires-Dist: click (==8.0.3)
Requires-Dist: rich (==10.12.0)
